PatternOmatic/__init__.py
PatternOmatic/api.py
PatternOmatic/ge/__init__.py
PatternOmatic/ge/individual.py
PatternOmatic/ge/population.py
PatternOmatic/ge/stats.py
PatternOmatic/nlp/__init__.py
PatternOmatic/nlp/bnf.py
PatternOmatic/settings/__init__.py
PatternOmatic/settings/config.py
PatternOmatic/settings/literals.py
PatternOmatic/settings/log.py
PatternOmatic-0.2.3.data/scripts/patternomatic.py
scripts/__init__.py
scripts/patternomatic.py
tests/__init__.py
tests/test_api.py
tests/test_bnf.py
tests/test_individual.py
tests/test_population.py
tests/test_script.py
tests/test_settings.py
tests/test_stats.py
PatternOmatic-0.2.3.dist-info/COPYING.LESSER.md
PatternOmatic-0.2.3.dist-info/COPYING.md
PatternOmatic-0.2.3.dist-info/METADATA
PatternOmatic-0.2.3.dist-info/WHEEL
PatternOmatic-0.2.3.dist-info/top_level.txt
PatternOmatic-0.2.3.dist-info/RECORD
