Metadata-Version: 2.1
Name: PatternOmatic
Version: 0.2.3
Summary: AI/NLP (Spacy) Rule Based Matcher pattern finder
Home-page: https://github.com/revuel/PatternOmatic
Author: Miguel Revuelta Espinosa
Author-email: revuel22@hotmail.com
License: UNKNOWN
Platform: UNKNOWN
Classifier: Programming Language :: Python :: 3
Classifier: License :: OSI Approved :: GNU Lesser General Public License v3 (LGPLv3)
Classifier: Operating System :: OS Independent
Requires-Python: >=3.7
Requires-Dist: spacy (==2.3.0)
